vectorDBpipe/__init__.py
vectorDBpipe/config/__init__.py
vectorDBpipe/config/config.yaml
vectorDBpipe/config/config_manager.py
vectorDBpipe/data/__init__.py
vectorDBpipe/data/loader.py
vectorDBpipe/embeddings/__init__.py
vectorDBpipe/embeddings/embedder.py
vectorDBpipe/logger/__init__.py
vectorDBpipe/logger/logging.py
vectorDBpipe/pipeline/__init__.py
vectorDBpipe/pipeline/text_pipeline.py
vectorDBpipe/tests/__init__.py
vectorDBpipe/tests/test_embedder.py
vectorDBpipe/tests/test_loader.py
vectorDBpipe/tests/test_pipeline.py
vectorDBpipe/tests/test_vectordb.py
vectorDBpipe/utils/__init__.py
vectorDBpipe/utils/common.py
vectorDBpipe/vectordb/__init__.py
vectorDBpipe/vectordb/store.py
vectordbpipe-0.1.2.dist-info/METADATA
vectordbpipe-0.1.2.dist-info/WHEEL
vectordbpipe-0.1.2.dist-info/top_level.txt
vectordbpipe-0.1.2.dist-info/RECORD
