Metadata-Version: 2.4
Name: vectordbpipe
Version: 0.1.2
Summary: A modular text embedding and vector database pipeline for local and cloud vector stores.
Author: Yash Desai
Author-email: desaisyash1000@gmail.com
License: MIT
Classifier: Programming Language :: Python :: 3
Classifier: License :: OSI Approved :: MIT License
Classifier: Operating System :: OS Independent
Requires-Python: >=3.8
Requires-Dist: PyYAML>=6.0
Requires-Dist: faiss-cpu>=1.7.4
Requires-Dist: sentence-transformers>=2.2.2
Requires-Dist: transformers>=4.28.1
Requires-Dist: torch>=2.2.0
Requires-Dist: torchvision
Requires-Dist: chromadb>=0.4.22
Requires-Dist: pinecone-client>=3.0.0
Requires-Dist: pandas>=2.0.0
Requires-Dist: tqdm>=4.66.0
Requires-Dist: docx2txt>=0.8
Requires-Dist: beautifulsoup4>=4.12.3
Requires-Dist: PyMuPDF>=1.23.26
Dynamic: author
Dynamic: author-email
Dynamic: classifier
Dynamic: description
Dynamic: description-content-type
Dynamic: license
Dynamic: requires-dist
Dynamic: requires-python
Dynamic: summary
